{
	"cmake" : 
	{
		"generator" : 
		{
			"multiConfig" : false,
			"name" : "NMake Makefiles JOM"
		},
		"paths" : 
		{
			"cmake" : "C:/Program Files/CMake/bin/cmake.exe",
			"cpack" : "C:/Program Files/CMake/bin/cpack.exe",
			"ctest" : "C:/Program Files/CMake/bin/ctest.exe",
			"root" : "C:/Program Files/CMake/share/cmake-4.2"
		},
		"version" : 
		{
			"isDirty" : false,
			"major" : 4,
			"minor" : 2,
			"patch" : 3,
			"string" : "4.2.3",
			"suffix" : ""
		}
	},
	"objects" : 
	[
		{
			"jsonFile" : "codemodel-v2-beb300aafa78781e9b4b.json",
			"kind" : "codemodel",
			"version" : 
			{
				"major" : 2,
				"minor" : 9
			}
		},
		{
			"jsonFile" : "cache-v2-4f663e0a5ab2e6dcbc3c.json",
			"kind" : "cache",
			"version" : 
			{
				"major" : 2,
				"minor" : 0
			}
		},
		{
			"jsonFile" : "cmakeFiles-v1-fb4f9dc64fbb6585986d.json",
			"kind" : "cmakeFiles",
			"version" : 
			{
				"major" : 1,
				"minor" : 1
			}
		}
	],
	"reply" : 
	{
		"cache-v2" : 
		{
			"jsonFile" : "cache-v2-4f663e0a5ab2e6dcbc3c.json",
			"kind" : "cache",
			"version" : 
			{
				"major" : 2,
				"minor" : 0
			}
		},
		"cmakeFiles-v1" : 
		{
			"jsonFile" : "cmakeFiles-v1-fb4f9dc64fbb6585986d.json",
			"kind" : "cmakeFiles",
			"version" : 
			{
				"major" : 1,
				"minor" : 1
			}
		},
		"codemodel-v2" : 
		{
			"jsonFile" : "codemodel-v2-beb300aafa78781e9b4b.json",
			"kind" : "codemodel",
			"version" : 
			{
				"major" : 2,
				"minor" : 9
			}
		}
	}
}
